sdk_ne/__init__.py
sdk_ne/sdk_ne.py
sdk_ne-1.0.0.dist-info/licenses/LICENSE.lic
sdk_ne-1.0.0.dist-info/METADATA
sdk_ne-1.0.0.dist-info/WHEEL
sdk_ne-1.0.0.dist-info/top_level.txt
sdk_ne-1.0.0.dist-info/RECORD
