Metadata-Version: 2.4
Name: sdk_ne
Version: 1.0.0
Summary: Log parameters, metrics, and artifacts using sdk.
Author: Saurav Kumar
Author-email: Saurav.Kumar@cognizant.com
Classifier: Programming Language :: Python :: 3
Classifier: License :: OSI Approved :: MIT License
Classifier: Operating System :: OS Independent
Requires-Python: >=3.6
License-File: LICENSE.lic
Dynamic: author
Dynamic: author-email
Dynamic: classifier
Dynamic: license-file
Dynamic: requires-python
Dynamic: summary
